archfinder/__init__.py
archfinder/__main__.py
archfinder/archfinder.py
archfinder-0.0.3.dist-info/LICENSE
archfinder-0.0.3.dist-info/METADATA
archfinder-0.0.3.dist-info/WHEEL
archfinder-0.0.3.dist-info/entry_points.txt
archfinder-0.0.3.dist-info/top_level.txt
archfinder-0.0.3.dist-info/RECORD
