Metadata-Version: 2.1
Name: archfinder
Version: 0.0.3
Summary: Arch Linux mirrorlist builder for pacman
Home-page: UNKNOWN
Author: Francisco Braço-Forte
Author-email: f.s.f.b2001@gmail.com
License: GPL-3.0-or-later
Platform: UNKNOWN
Requires-Python: >=3.8, <4
License-File: LICENSE
Requires-Dist: urllib3 (==1.26.5)
